spay/__init__.py
spay/client.py
spay/configs.py
spay-3.0.0.dist-info/METADATA
spay-3.0.0.dist-info/WHEEL
spay-3.0.0.dist-info/top_level.txt
spay-3.0.0.dist-info/RECORD
