Metadata-Version: 2.4
Name: spay
Version: 3.0.0
Summary: Python SDK for Spay internet gateway
Author: Saba Pardazesh
Author-email: info@spay.ir
Requires-Python: >=3.8
Requires-Dist: requests>=2.31.0
Dynamic: author
Dynamic: author-email
Dynamic: description
Dynamic: description-content-type
Dynamic: requires-dist
Dynamic: requires-python
Dynamic: summary
